Fermat_Factoring/FermatFactorization.py
Fermat_Factoring/__init__.py
Fermat_Factoring-0.0.2.dist-info/LICENSE.txt
Fermat_Factoring-0.0.2.dist-info/METADATA
Fermat_Factoring-0.0.2.dist-info/WHEEL
Fermat_Factoring-0.0.2.dist-info/top_level.txt
Fermat_Factoring-0.0.2.dist-info/RECORD
