Metadata-Version: 2.1
Name: Fermat-Factoring
Version: 0.0.2
Summary: Factorising integers based on Fermat's technique
Home-page: https://github.com/mihirgit/Fermat_Factoring
Author: Mihir Goyenka
Author-email: mihirgoyenka@gmail.com
License: UNKNOWN
Platform: UNKNOWN
Classifier: Programming Language :: Python :: 3
Classifier: License :: OSI Approved :: MIT License
Classifier: Operating System :: OS Independent
Requires-Python: >=3.8
